README.md
pyproject.toml
setup.py
wiser/__init__.py
wiser.egg-info/PKG-INFO
wiser.egg-info/SOURCES.txt
wiser.egg-info/dependency_links.txt
wiser.egg-info/namespace_packages.txt
wiser.egg-info/not-zip-safe
wiser.egg-info/requires.txt
wiser.egg-info/top_level.txt
wiser/core/__init__.py
wiser/core/types/__init__.py
wiser/core/types/extensions.py